rvc_cli/__init__.py
rvc_cli/core.py
rvc_cli/rvc/__init__.py
rvc_cli/rvc/configs/__init__.py
rvc_cli/rvc/configs/config.py
rvc_cli/rvc/configs/v1/__init__.py
rvc_cli/rvc/configs/v2/__init__.py
rvc_cli/rvc/infer/__init__.py
rvc_cli/rvc/infer/infer.py
rvc_cli/rvc/infer/pipeline.py
rvc_cli/rvc/lib/__init__.py
rvc_cli/rvc/lib/utils.py
rvc_cli/rvc/lib/zluda.py
rvc_cli/rvc/lib/algorithm/__init__.py
rvc_cli/rvc/lib/algorithm/attentions.py
rvc_cli/rvc/lib/algorithm/commons.py
rvc_cli/rvc/lib/algorithm/discriminators.py
rvc_cli/rvc/lib/algorithm/encoders.py
rvc_cli/rvc/lib/algorithm/generators.py
rvc_cli/rvc/lib/algorithm/modules.py
rvc_cli/rvc/lib/algorithm/normalization.py
rvc_cli/rvc/lib/algorithm/nsf.py
rvc_cli/rvc/lib/algorithm/residuals.py
rvc_cli/rvc/lib/algorithm/synthesizers.py
rvc_cli/rvc/lib/predictors/F0Extractor.py
rvc_cli/rvc/lib/predictors/FCPE.py
rvc_cli/rvc/lib/predictors/RMVPE.py
rvc_cli/rvc/lib/predictors/__init__.py
rvc_cli/rvc/lib/tools/__init__.py
rvc_cli/rvc/lib/tools/analyzer.py
rvc_cli/rvc/lib/tools/gdown.py
rvc_cli/rvc/lib/tools/launch_tensorboard.py
rvc_cli/rvc/lib/tools/model_download.py
rvc_cli/rvc/lib/tools/prerequisites_download.py
rvc_cli/rvc/lib/tools/pretrained_selector.py
rvc_cli/rvc/lib/tools/split_audio.py
rvc_cli-1.7.0.dist-info/LICENSE
rvc_cli-1.7.0.dist-info/METADATA
rvc_cli-1.7.0.dist-info/WHEEL
rvc_cli-1.7.0.dist-info/entry_points.txt
rvc_cli-1.7.0.dist-info/top_level.txt
rvc_cli-1.7.0.dist-info/RECORD
